wxautox/__init__.py
wxautox/__main__.py
wxautox/exceptions.py
wxautox/languages.py
wxautox/logger.py
wxautox/msgs/__init__.py
wxautox/msgs/base.cp311-win_amd64.pyd
wxautox/msgs/base.pyi
wxautox/msgs/friend.cp311-win_amd64.pyd
wxautox/msgs/mattr.cp311-win_amd64.pyd
wxautox/msgs/mattr.pyi
wxautox/msgs/msg.cp311-win_amd64.pyd
wxautox/msgs/self.cp311-win_amd64.pyd
wxautox/msgs/type.cp311-win_amd64.pyd
wxautox/msgs/type.pyi
wxautox/param.py
wxautox/ui/__init__.py
wxautox/ui/base.py
wxautox/ui/browser.py
wxautox/ui/chatbox.cp311-win_amd64.pyd
wxautox/ui/component.cp311-win_amd64.pyd
wxautox/ui/main.cp311-win_amd64.pyd
wxautox/ui/moment.cp311-win_amd64.pyd
wxautox/ui/navigationbox.cp311-win_amd64.pyd
wxautox/ui/sessionbox.cp311-win_amd64.pyd
wxautox/uia/__init__.py
wxautox/uia/uiautomation.py
wxautox/uia/uiplug.cp311-win_amd64.pyd
wxautox/utils/__init__.py
wxautox/utils/lock.py
wxautox/utils/tools.cp311-win_amd64.pyd
wxautox/utils/useful.cp311-win_amd64.pyd
wxautox/utils/win32.cp311-win_amd64.pyd
wxautox/wx.cp311-win_amd64.pyd
wxautox/wx.pyi
wxautox-39.1.41.dist-info/entry_points.txt
wxautox-39.1.41.dist-info/METADATA
wxautox-39.1.41.dist-info/WHEEL
wxautox-39.1.41.dist-info/RECORD
